ogr/__init__.py
ogr/constant.py
ogr/deprecation.py
ogr/exceptions.py
ogr/factory.py
ogr/parsing.py
ogr/py.typed
ogr/read_only.py
ogr/utils.py
ogr/abstract/__init__.py
ogr/abstract/abstract_class.py
ogr/abstract/access_level.py
ogr/abstract/auth_method.py
ogr/abstract/comment.py
ogr/abstract/commit_flag.py
ogr/abstract/exception.py
ogr/abstract/git_project.py
ogr/abstract/git_service.py
ogr/abstract/git_tag.py
ogr/abstract/git_user.py
ogr/abstract/issue.py
ogr/abstract/label.py
ogr/abstract/pull_request.py
ogr/abstract/release.py
ogr/abstract/status.py
ogr/services/__init__.py
ogr/services/base.py
ogr/services/forgejo/__init__.py
ogr/services/forgejo/flag.py
ogr/services/forgejo/issue.py
ogr/services/forgejo/label.py
ogr/services/forgejo/project.py
ogr/services/forgejo/pull_request.py
ogr/services/forgejo/release.py
ogr/services/forgejo/service.py
ogr/services/forgejo/user.py
ogr/services/forgejo/utils.py
ogr/services/github/__init__.py
ogr/services/github/check_run.py
ogr/services/github/comments.py
ogr/services/github/flag.py
ogr/services/github/issue.py
ogr/services/github/label.py
ogr/services/github/project.py
ogr/services/github/pull_request.py
ogr/services/github/release.py
ogr/services/github/service.py
ogr/services/github/user.py
ogr/services/github/auth_providers/__init__.py
ogr/services/github/auth_providers/abstract.py
ogr/services/github/auth_providers/github_app.py
ogr/services/github/auth_providers/token.py
ogr/services/github/auth_providers/tokman.py
ogr/services/gitlab/__init__.py
ogr/services/gitlab/comments.py
ogr/services/gitlab/flag.py
ogr/services/gitlab/issue.py
ogr/services/gitlab/label.py
ogr/services/gitlab/project.py
ogr/services/gitlab/pull_request.py
ogr/services/gitlab/release.py
ogr/services/gitlab/service.py
ogr/services/gitlab/user.py
ogr/services/pagure/__init__.py
ogr/services/pagure/comments.py
ogr/services/pagure/flag.py
ogr/services/pagure/group.py
ogr/services/pagure/issue.py
ogr/services/pagure/label.py
ogr-0.60.1.dist-info/METADATA
ogr-0.60.1.dist-info/WHEEL
ogr-0.60.1.dist-info/licenses/LICENSE
ogr-0.60.1.dist-info/RECORD
