Metadata-Version: 2.4
Name: ogr
Version: 0.60.1
Summary: One API for multiple git forges.
Project-URL: Homepage, https://github.com/packit/ogr
Author-email: Red Hat <user-cont-team@redhat.com>
License-Expression: MIT
License-File: LICENSE
Keywords: api,forgejo,git,github,gitlab,pagure
Classifier: Development Status :: 4 - Beta
Classifier: Intended Audience :: Developers
Classifier: License :: OSI Approved :: MIT License
Classifier: Operating System :: POSIX :: Linux
Classifier: Programming Language :: Python
Classifier: Programming Language :: Python :: 3
Classifier: Programming Language :: Python :: 3 :: Only
Classifier: Programming Language :: Python :: 3.9
Classifier: Programming Language :: Python :: 3.10
Classifier: Programming Language :: Python :: 3.11
Classifier: Topic :: Software Development
Classifier: Topic :: Utilities
Requires-Python: >=3.9
Requires-Dist: cryptography
Requires-Dist: deprecated
Requires-Dist: gitpython
Requires-Dist: httpx
Requires-Dist: pyforgejo>=2.0.0
Requires-Dist: pygithub
Requires-Dist: python-gitlab
Requires-Dist: pyyaml
Requires-Dist: requests
Requires-Dist: urllib3
Provides-Extra: testing
Requires-Dist: flexmock; extra == 'testing'
Requires-Dist: pytest; extra == 'testing'
Requires-Dist: pytest-cov; extra == 'testing'
